{"customerNae": "Test1","customerOrganizationNumber": "111111-1111","organizationName": "OrgTest1","organizationNumber": "111112-1112","organizationTenantId": "a56ee6ba-7c24-45df-9a97-692a4dde1c2b","transactionType": "AUTO_INVOICE","transactionDate": "2023-09-04","quantity": 19} {"customerName": "Test1","customerOrganizationNumber": "111111-1111","organizationName": "OrgTest1","organizationNumber": "111112-1112","organizationTenantId": "a56ee6ba-7c24-45df-9a97-692a4dde1c2b","transactionType": "MANUAL","transactionDate": "2023-09-04","quantity": 42} {"customerName": "Test2","customerOrganizationNumber": "222222-2222","organizationName": "OrgTest2","organizationNumber": "222223-2223","organizationTenantId": "35055736-882f-4c28-a435-5ec36f37793e","transactionType": "MANUAL","transactionDate": "2023-09-04","quantity": 20}
